[
 {
  "name": "pmc_hum_chris_v3_head",
  "hash": "0xAB8BAD43",
  "w": 512,
  "h": 512,
  "tris": 15998
 },
 {
  "name": "tex_0xCFC87639",
  "hash": "0xCFC87639",
  "w": 256,
  "h": 256,
  "tris": 12687
 },
 {
  "name": "pmc_hum_chris_v3_lb",
  "hash": "0x5D16F3CB",
  "w": 512,
  "h": 512,
  "tris": 10331
 },
 {
  "name": "pmc_hum_chris_v3_ub",
  "hash": "0x4D17AFBC",
  "w": 512,
  "h": 512,
  "tris": 11092
 },
 {
  "name": "pmc_hum_chris_eyes",
  "hash": "0x82569011",
  "w": 128,
  "h": 128,
  "tris": 344
 },
 {
  "name": "tex_0x5AAB9E8A",
  "hash": "0x5AAB9E8A",
  "w": 64,
  "h": 64,
  "tris": 312
 },
 {
  "name": "tex_0xE27C6F51",
  "hash": "0xE27C6F51",
  "w": 64,
  "h": 128,
  "tris": 3728
 }
]